scraibe_webui/__init__.py
scraibe_webui/_version.py
scraibe_webui/app.py
scraibe_webui/cli.py
scraibe_webui/global_var.py
scraibe_webui/misc/config.yaml
scraibe_webui/misc/error_notification_template.html
scraibe_webui/misc/footer.html
scraibe_webui/misc/footer_style.css
scraibe_webui/misc/header.html
scraibe_webui/misc/header_style.css
scraibe_webui/misc/logo.png
scraibe_webui/misc/mail_style.css
scraibe_webui/misc/success_template.html
scraibe_webui/misc/upload_notification_template.html
scraibe_webui/ui.py
scraibe_webui/utils/__init__.py
scraibe_webui/utils/_parsekwargs.py
scraibe_webui/utils/appconfigloader.py
scraibe_webui/utils/background.py
scraibe_webui/utils/configloader.py
scraibe_webui/utils/interactions.py
scraibe_webui/utils/lang.py
scraibe_webui/utils/mail.py
scraibe_webui/utils/themes.py
scraibe_webui/utils/wrapper.py
scraibe_webui-0.2.1.dist-info/LICENSE
scraibe_webui-0.2.1.dist-info/METADATA
scraibe_webui-0.2.1.dist-info/WHEEL
scraibe_webui-0.2.1.dist-info/entry_points.txt
scraibe_webui-0.2.1.dist-info/RECORD
