Metadata-Version: 2.1
Name: scraibe-webui
Version: 0.2.1
Summary: A web interface for the ScAIbe speech-to-text transcription tool
Home-page: https://github.com/JSchmie/ScrAIbe-WebUI
License: GPL-3.0-or-later
Keywords: gradio,webui,whisper,pyannote,speech-to-text,speech-recognition
Author: Schmieder, Jacob
Author-email: jacob.schmieder@dbfz.de
Requires-Python: >=3.10,<4.0
Classifier: Development Status :: 4 - Beta
Classifier: Environment :: GPU :: NVIDIA CUDA :: 12 :: 12.1
Classifier: Framework :: FastAPI
Classifier: Intended Audience :: Developers
Classifier: License :: OSI Approved :: GNU General Public License v3 (GPLv3)
Classifier: License :: OSI Approved :: GNU General Public License v3 or later (GPLv3+)
Classifier: Programming Language :: Python :: 3
Classifier: Programming Language :: Python :: 3.10
Classifier: Programming Language :: Python :: 3.11
Classifier: Programming Language :: Python :: 3.12
Classifier: Programming Language :: Python :: 3.13
Classifier: Programming Language :: Python :: 3.8
Classifier: Programming Language :: Python :: 3.9
Classifier: Topic :: Scientific/Engineering :: Artificial Intelligence
Requires-Dist: gradio (>=5.5,<5.6)
Requires-Dist: pandas (>=2.2.2,<3.0.0)
Requires-Dist: scraibe (>=0.3.0,<0.4.0)
Requires-Dist: tqdm (>=4.66.5,<5.0.0)
Project-URL: Repository, https://github.com/JSchmie/ScrAIbe-WebUI
